pandas-stubs/__init__.pyi
pandas-stubs/_config/__init__.pyi
pandas-stubs/_config/config.pyi
pandas-stubs/_libs/__init__.pyi
pandas-stubs/_libs/indexing.pyi
pandas-stubs/_libs/interval.pyi
pandas-stubs/_libs/json.pyi
pandas-stubs/_libs/lib.pyi
pandas-stubs/_libs/missing.pyi
pandas-stubs/_libs/properties.pyi
pandas-stubs/_libs/sparse.pyi
pandas-stubs/_libs/tslibs/__init__.pyi
pandas-stubs/_libs/tslibs/base.pyi
pandas-stubs/_libs/tslibs/conversion.pyi
pandas-stubs/_libs/tslibs/nattype.pyi
pandas-stubs/_libs/tslibs/np_datetime.pyi
pandas-stubs/_libs/tslibs/offsets.pyi
pandas-stubs/_libs/tslibs/parsing.pyi
pandas-stubs/_libs/tslibs/period.pyi
pandas-stubs/_libs/tslibs/timedeltas.pyi
pandas-stubs/_libs/tslibs/timestamps.pyi
pandas-stubs/_libs/window/__init__.pyi
pandas-stubs/_testing/__init__.pyi
pandas-stubs/_typing.pyi
pandas-stubs/_version.pyi
pandas-stubs/api/__init__.pyi
pandas-stubs/api/extensions/__init__.pyi
pandas-stubs/api/indexers/__init__.pyi
pandas-stubs/api/interchange/__init__.pyi
pandas-stubs/api/types/__init__.pyi
pandas-stubs/api/typing/__init__.pyi
pandas-stubs/arrays/__init__.pyi
pandas-stubs/core/__init__.pyi
pandas-stubs/core/accessor.pyi
pandas-stubs/core/algorithms.pyi
pandas-stubs/core/api.pyi
pandas-stubs/core/arraylike.pyi
pandas-stubs/core/arrays/__init__.pyi
pandas-stubs/core/arrays/arrow/dtype.pyi
pandas-stubs/core/arrays/base.pyi
pandas-stubs/core/arrays/boolean.pyi
pandas-stubs/core/arrays/categorical.pyi
pandas-stubs/core/arrays/datetimelike.pyi
pandas-stubs/core/arrays/datetimes.pyi
pandas-stubs/core/arrays/floating.pyi
pandas-stubs/core/arrays/integer.pyi
pandas-stubs/core/arrays/interval.pyi
pandas-stubs/core/arrays/masked.pyi
pandas-stubs/core/arrays/numeric.pyi
pandas-stubs/core/arrays/numpy_.pyi
pandas-stubs/core/arrays/period.pyi
pandas-stubs/core/arrays/sparse/__init__.pyi
pandas-stubs/core/arrays/sparse/accessor.pyi
pandas-stubs/core/arrays/sparse/array.pyi
pandas-stubs/core/arrays/sparse/dtype.pyi
pandas_stubs-2.3.0.250702.dist-info/LICENSE
pandas_stubs-2.3.0.250702.dist-info/METADATA
pandas_stubs-2.3.0.250702.dist-info/WHEEL
pandas_stubs-2.3.0.250702.dist-info/RECORD
