Metadata-Version: 2.1
Name: pandas-stubs
Version: 2.3.0.250702
Summary: Type annotations for pandas
Home-page: https://pandas.pydata.org
License: BSD-3-Clause
Author: The Pandas Development Team
Author-email: pandas-dev@python.org
Requires-Python: >=3.10
Classifier: Development Status :: 5 - Production/Stable
Classifier: Environment :: Console
Classifier: Intended Audience :: Science/Research
Classifier: License :: OSI Approved :: BSD License
Classifier: Operating System :: OS Independent
Classifier: Programming Language :: Python
Classifier: Programming Language :: Python :: 3
Classifier: Programming Language :: Python :: 3.10
Classifier: Programming Language :: Python :: 3.11
Classifier: Programming Language :: Python :: 3.12
Classifier: Programming Language :: Python :: 3 :: Only
Classifier: Programming Language :: Python :: 3.13
Classifier: Topic :: Scientific/Engineering
Classifier: Typing :: Stubs Only
Requires-Dist: numpy (>=1.23.5)
Requires-Dist: pyrefly (>=0.21.0,<0.22.0)
Requires-Dist: ty (>=0.0.1a8,<0.0.2)
Requires-Dist: types-pytz (>=2022.1.1)
Project-URL: Bug Tracker, https://github.com/pandas-dev/pandas-stubs/issues
Project-URL: Documentation, https://pandas.pydata.org/pandas-docs/stable
Project-URL: Repository, https://github.com/pandas-dev/pandas-stubs
